// class version 50.0 (50)
// access flags 0x21
public class com/xtremelabs/robolectric/bytecode/InstrumentingClassLoaderTest$ClassWithFunnyConstructors {

  // compiled from: InstrumentingClassLoaderTest.java

  @Lcom/xtremelabs/robolectric/internal/Instrument;()
  // access flags 0x9
  public static INNERCLASS com/xtremelabs/robolectric/bytecode/InstrumentingClassLoaderTest$UninstrumentedParent com/xtremelabs/robolectric/bytecode/InstrumentingClassLoaderTest UninstrumentedParent
  // access flags 0x9
  public static INNERCLASS com/xtremelabs/robolectric/bytecode/InstrumentingClassLoaderTest$ClassWithFunnyConstructors com/xtremelabs/robolectric/bytecode/InstrumentingClassLoaderTest ClassWithFunnyConstructors

  // access flags 0x12
  private final Lcom/xtremelabs/robolectric/bytecode/InstrumentingClassLoaderTest$UninstrumentedParent; uninstrumentedParent

  // access flags 0x2
  private Ljava/lang/String; name

  // access flags 0x1
  // signature Ljava/lang/Object;
  // declaration: 
  public Ljava/lang/Object; __robo_data__

  // access flags 0x1
  public $$robo$$InstrumentingClassLoaderTest$ClassWithFunnyConstructors_d738___constructor__(Ljava/lang/String;)V
   L0
    LINENUMBER 329 L0
    ALOAD 0
    ALOAD 1
    PUTFIELD com/xtremelabs/robolectric/bytecode/InstrumentingClassLoaderTest$ClassWithFunnyConstructors.name : Ljava/lang/String;
   L1
    LINENUMBER 330 L1
    RETURN
   L2
    LOCALVARIABLE this Lcom/xtremelabs/robolectric/bytecode/InstrumentingClassLoaderTest$ClassWithFunnyConstructors; L0 L2 0
    LOCALVARIABLE name Ljava/lang/String; L0 L2 1
    MAXSTACK = 4
    MAXLOCALS = 2

  // access flags 0x1
  public $$robo$$InstrumentingClassLoaderTest$ClassWithFunnyConstructors_d738___constructor__(Lcom/xtremelabs/robolectric/bytecode/InstrumentingClassLoaderTest$UninstrumentedParent;Ljava/lang/String;)V
   L0
    LINENUMBER 333 L0
    ALOAD 0
    ALOAD 1
    PUTFIELD com/xtremelabs/robolectric/bytecode/InstrumentingClassLoaderTest$ClassWithFunnyConstructors.uninstrumentedParent : Lcom/xtremelabs/robolectric/bytecode/InstrumentingClassLoaderTest$UninstrumentedParent;
   L1
    LINENUMBER 334 L1
    RETURN
   L2
    LOCALVARIABLE this Lcom/xtremelabs/robolectric/bytecode/InstrumentingClassLoaderTest$ClassWithFunnyConstructors; L0 L2 0
    LOCALVARIABLE uninstrumentedParent Lcom/xtremelabs/robolectric/bytecode/InstrumentingClassLoaderTest$UninstrumentedParent; L0 L2 1
    LOCALVARIABLE fooString Ljava/lang/String; L0 L2 2
    MAXSTACK = 2
    MAXLOCALS = 3

  // access flags 0x0
  __constructor__(Ljava/lang/String;)V
    ALOAD 0
    ALOAD 1
    INVOKESPECIAL com/xtremelabs/robolectric/bytecode/InstrumentingClassLoaderTest$ClassWithFunnyConstructors.$$robo$$InstrumentingClassLoaderTest$ClassWithFunnyConstructors_d738___constructor__ (Ljava/lang/String;)V
    RETURN
    MAXSTACK = 2
    MAXLOCALS = 2

public com.xtremelabs.robolectric.bytecode.InstrumentingClassLoaderTest$ClassWithFunnyConstructors(java.lang.String);
  Code:
   0:	aload_0
   1:	new	#1; //class com/xtremelabs/robolectric/bytecode/InstrumentingClassLoaderTest$UninstrumentedParent
   4:	dup
   5:	aload_1
   6:	invokespecial	#2; //Method com/xtremelabs/robolectric/bytecode/InstrumentingClassLoaderTest$UninstrumentedParent."<init>":(Ljava/lang/String;)V
   9:	ldc	#3; //String foo
   11:	invokespecial	#4; //Method "<init>":(Lcom/xtremelabs/robolectric/bytecode/InstrumentingClassLoaderTest$UninstrumentedParent;Ljava/lang/String;)V
   14:	return

  // access flags 0x1
  public <init>(Ljava/lang/String;)V
   L0
    LINENUMBER 328 L0
    ALOAD 0
    NEW com/xtremelabs/robolectric/bytecode/InstrumentingClassLoaderTest$UninstrumentedParent
    DUP
    ALOAD 1
    INVOKESPECIAL com/xtremelabs/robolectric/bytecode/InstrumentingClassLoaderTest$UninstrumentedParent.<init> (Ljava/lang/String;)V
    LDC "foo"
    INVOKESPECIAL com/xtremelabs/robolectric/bytecode/InstrumentingClassLoaderTest$ClassWithFunnyConstructors.<init> (Lcom/xtremelabs/robolectric/bytecode/InstrumentingClassLoaderTest$UninstrumentedParent;Ljava/lang/String;)V
    LDC Lcom/xtremelabs/robolectric/bytecode/InstrumentingClassLoaderTest$ClassWithFunnyConstructors;.class
    LDC "__constructor__"
    ALOAD 0
    ICONST_1
    ANEWARRAY java/lang/String
    DUP
    ICONST_0
    LDC "java.lang.String"
    AASTORE
    ICONST_1
    ANEWARRAY java/lang/Object
    DUP
    ICONST_0
    ALOAD 1
    AASTORE
    INVOKESTATIC com/xtremelabs/robolectric/bytecode/RobolectricInternals.methodInvoked (Ljava/lang/Class;Ljava/lang/String;Ljava/lang/Object;[Ljava/lang/String;[Ljava/lang/Object;)Ljava/lang/Object;
    RETURN
    MAXSTACK = 8
    MAXLOCALS = 2

  // access flags 0x0
  __constructor__(Lcom/xtremelabs/robolectric/bytecode/InstrumentingClassLoaderTest$UninstrumentedParent;Ljava/lang/String;)V
    ALOAD 0
    ALOAD 1
    ALOAD 2
    INVOKESPECIAL com/xtremelabs/robolectric/bytecode/InstrumentingClassLoaderTest$ClassWithFunnyConstructors.$$robo$$InstrumentingClassLoaderTest$ClassWithFunnyConstructors_d738___constructor__ (Lcom/xtremelabs/robolectric/bytecode/InstrumentingClassLoaderTest$UninstrumentedParent;Ljava/lang/String;)V
    RETURN
    MAXSTACK = 3
    MAXLOCALS = 3

public com.xtremelabs.robolectric.bytecode.InstrumentingClassLoaderTest$ClassWithFunnyConstructors(com.xtremelabs.robolectric.bytecode.InstrumentingClassLoaderTest$UninstrumentedParent, java.lang.String);
  Code:
   0:	aload_0
   1:	invokespecial	#5; //Method java/lang/Object."<init>":()V
   4:	aload_0
   5:	aload_1
   6:	putfield	#6; //Field uninstrumentedParent:Lcom/xtremelabs/robolectric/bytecode/InstrumentingClassLoaderTest$UninstrumentedParent;
   9:	return

}

  // access flags 0x1
  public <init>(Lcom/xtremelabs/robolectric/bytecode/InstrumentingClassLoaderTest$UninstrumentedParent;Ljava/lang/String;)V
   L0
    LINENUMBER 332 L0
    ALOAD 0
    INVOKESPECIAL java/lang/Object.<init> ()V
    LDC Lcom/xtremelabs/robolectric/bytecode/InstrumentingClassLoaderTest$ClassWithFunnyConstructors;.class
    LDC "__constructor__"
    ALOAD 0
    ICONST_2
    ANEWARRAY java/lang/String
    DUP
    ICONST_0
    LDC "com.xtremelabs.robolectric.bytecode.InstrumentingClassLoaderTest$UninstrumentedParent"
    AASTORE
    DUP
    ICONST_1
    LDC "java.lang.String"
    AASTORE
    ICONST_2
    ANEWARRAY java/lang/Object
    DUP
    ICONST_0
    ALOAD 1
    AASTORE
    DUP
    ICONST_1
    ALOAD 2
    AASTORE
    INVOKESTATIC com/xtremelabs/robolectric/bytecode/RobolectricInternals.methodInvoked (Ljava/lang/Class;Ljava/lang/String;Ljava/lang/Object;[Ljava/lang/String;[Ljava/lang/Object;)Ljava/lang/Object;
    RETURN
    MAXSTACK = 8
    MAXLOCALS = 3

  // access flags 0x1
  // signature ()V
  // declaration: void <init>()
  public <init>()V
    ALOAD 0
    INVOKESPECIAL java/lang/Object.<init> ()V
    RETURN
    MAXSTACK = 1
    MAXLOCALS = 1

  // access flags 0x1
  public <init>(Lcom/xtremelabs/robolectric/bytecode/DirectObjectMarker;Lcom/xtremelabs/robolectric/bytecode/InstrumentingClassLoaderTest$ClassWithFunnyConstructors;)V
    ALOAD 0
    INVOKESPECIAL java/lang/Object.<init> ()V
    ALOAD 0
    ALOAD 2
    PUTFIELD com/xtremelabs/robolectric/bytecode/InstrumentingClassLoaderTest$ClassWithFunnyConstructors.__robo_data__ : Ljava/lang/Object;
    RETURN
    MAXSTACK = 2
    MAXLOCALS = 3
}
