// class version 49.0 (49)
// access flags 0x21
public class com/google/android/maps/GeoPoint {


  // access flags 0x1
  // signature Ljava/lang/Object;
  // declaration: 
  public Ljava/lang/Object; __robo_data__

  // access flags 0x1
  public $$robo$$GeoPoint_bc6f___constructor__(II)V
   L0
    RETURN
    LOCALVARIABLE this Lcom/android/mkstubs/stubber/MethodStubber; L0 L0 0
    MAXSTACK = 3
    MAXLOCALS = 3

  // access flags 0x1
  public $$robo$$getLatitudeE6()I
   L0
    LINENUMBER 36 L0
    NEW java/lang/RuntimeException
    DUP
    LDC "stub"
    INVOKESPECIAL java/lang/RuntimeException.<init> (Ljava/lang/String;)V
    ATHROW
   L1
    LOCALVARIABLE this Lcom/android/mkstubs/stubber/MethodStubber; L0 L1 0
    MAXSTACK = 3
    MAXLOCALS = 1

  // access flags 0x1
  public $$robo$$getLongitudeE6()I
   L0
    LINENUMBER 36 L0
    NEW java/lang/RuntimeException
    DUP
    LDC "stub"
    INVOKESPECIAL java/lang/RuntimeException.<init> (Ljava/lang/String;)V
    ATHROW
   L1
    LOCALVARIABLE this Lcom/android/mkstubs/stubber/MethodStubber; L0 L1 0
    MAXSTACK = 3
    MAXLOCALS = 1

  // access flags 0x1
  public $$robo$$toString()Ljava/lang/String;
   L0
    LINENUMBER 36 L0
    NEW java/lang/RuntimeException
    DUP
    LDC "stub"
    INVOKESPECIAL java/lang/RuntimeException.<init> (Ljava/lang/String;)V
    ATHROW
   L1
    LOCALVARIABLE this Lcom/android/mkstubs/stubber/MethodStubber; L0 L1 0
    MAXSTACK = 3
    MAXLOCALS = 1

  // access flags 0x1
  public $$robo$$equals(Ljava/lang/Object;)Z
   L0
    LINENUMBER 36 L0
    NEW java/lang/RuntimeException
    DUP
    LDC "stub"
    INVOKESPECIAL java/lang/RuntimeException.<init> (Ljava/lang/String;)V
    ATHROW
   L1
    LOCALVARIABLE this Lcom/android/mkstubs/stubber/MethodStubber; L0 L1 0
    MAXSTACK = 3
    MAXLOCALS = 2

  // access flags 0x1
  public $$robo$$hashCode()I
   L0
    LINENUMBER 36 L0
    NEW java/lang/RuntimeException
    DUP
    LDC "stub"
    INVOKESPECIAL java/lang/RuntimeException.<init> (Ljava/lang/String;)V
    ATHROW
   L1
    LOCALVARIABLE this Lcom/android/mkstubs/stubber/MethodStubber; L0 L1 0
    MAXSTACK = 3
    MAXLOCALS = 1

  // access flags 0x0
  __constructor__(II)V
    ALOAD 0
    ILOAD 1
    ILOAD 2
    INVOKESPECIAL com/google/android/maps/GeoPoint.$$robo$$GeoPoint_bc6f___constructor__ (II)V
    RETURN
    MAXSTACK = 3
    MAXLOCALS = 3

  // access flags 0x1
  public <init>(II)V
   L0
    LINENUMBER 36 L0
    NEW java/lang/RuntimeException
    DUP
    LDC "stub"
    INVOKESPECIAL java/lang/RuntimeException.<init> (Ljava/lang/String;)V
    ATHROW
    LDC Lcom/google/android/maps/GeoPoint;.class
    LDC "__constructor__"
    ALOAD 0
    ICONST_2
    ANEWARRAY java/lang/String
    DUP
    ICONST_0
    LDC "int"
    AASTORE
    DUP
    ICONST_1
    LDC "int"
    AASTORE
    ICONST_2
    ANEWARRAY java/lang/Object
    DUP
    ICONST_0
    ILOAD 1
    NEW java/lang/Integer
    DUP_X1
    SWAP
    INVOKESPECIAL java/lang/Integer.<init> (I)V
    AASTORE
    DUP
    ICONST_1
    ILOAD 2
    NEW java/lang/Integer
    DUP_X1
    SWAP
    INVOKESPECIAL java/lang/Integer.<init> (I)V
    AASTORE
    INVOKESTATIC com/xtremelabs/robolectric/bytecode/RobolectricInternals.methodInvoked (Ljava/lang/Class;Ljava/lang/String;Ljava/lang/Object;[Ljava/lang/String;[Ljava/lang/Object;)Ljava/lang/Object;
    RETURN
    MAXSTACK = 3
    MAXLOCALS = 3

  // access flags 0x0
  $$robo$$GeoPoint_bc6f_getLatitudeE6()I
    ALOAD 0
    INVOKESPECIAL com/google/android/maps/GeoPoint.$$robo$$getLatitudeE6 ()I
    IRETURN
    MAXSTACK = 1
    MAXLOCALS = 1

  // access flags 0x1
  public getLatitudeE6()I
    ALOAD 0
    GETFIELD com/google/android/maps/GeoPoint.__robo_data__ : Ljava/lang/Object;
    INSTANCEOF com/google/android/maps/GeoPoint
    IFNE L0
    ALOAD 0
    INVOKESTATIC com/xtremelabs/robolectric/bytecode/RobolectricInternals.shouldCallDirectly (Ljava/lang/Object;)Z
    IFEQ L1
   L0
    ALOAD 0
    INVOKESPECIAL com/google/android/maps/GeoPoint.$$robo$$getLatitudeE6 ()I
    IRETURN
   L1
    LDC Lcom/google/android/maps/GeoPoint;.class
    LDC "getLatitudeE6"
    ALOAD 0
    ICONST_0
    ANEWARRAY java/lang/String
    ICONST_0
    ANEWARRAY java/lang/Object
    INVOKESTATIC com/xtremelabs/robolectric/bytecode/RobolectricInternals.methodInvoked (Ljava/lang/Class;Ljava/lang/String;Ljava/lang/Object;[Ljava/lang/String;[Ljava/lang/Object;)Ljava/lang/Object;
    DUP
    IFNONNULL L2
    POP
    ICONST_0
    GOTO L3
   L2
    CHECKCAST java/lang/Number
    INVOKEVIRTUAL java/lang/Number.intValue ()I
   L3
    IRETURN
    MAXSTACK = 5
    MAXLOCALS = 1

  // access flags 0x0
  $$robo$$GeoPoint_bc6f_getLongitudeE6()I
    ALOAD 0
    INVOKESPECIAL com/google/android/maps/GeoPoint.$$robo$$getLongitudeE6 ()I
    IRETURN
    MAXSTACK = 1
    MAXLOCALS = 1

  // access flags 0x1
  public getLongitudeE6()I
    ALOAD 0
    GETFIELD com/google/android/maps/GeoPoint.__robo_data__ : Ljava/lang/Object;
    INSTANCEOF com/google/android/maps/GeoPoint
    IFNE L0
    ALOAD 0
    INVOKESTATIC com/xtremelabs/robolectric/bytecode/RobolectricInternals.shouldCallDirectly (Ljava/lang/Object;)Z
    IFEQ L1
   L0
    ALOAD 0
    INVOKESPECIAL com/google/android/maps/GeoPoint.$$robo$$getLongitudeE6 ()I
    IRETURN
   L1
    LDC Lcom/google/android/maps/GeoPoint;.class
    LDC "getLongitudeE6"
    ALOAD 0
    ICONST_0
    ANEWARRAY java/lang/String
    ICONST_0
    ANEWARRAY java/lang/Object
    INVOKESTATIC com/xtremelabs/robolectric/bytecode/RobolectricInternals.methodInvoked (Ljava/lang/Class;Ljava/lang/String;Ljava/lang/Object;[Ljava/lang/String;[Ljava/lang/Object;)Ljava/lang/Object;
    DUP
    IFNONNULL L2
    POP
    ICONST_0
    GOTO L3
   L2
    CHECKCAST java/lang/Number
    INVOKEVIRTUAL java/lang/Number.intValue ()I
   L3
    IRETURN
    MAXSTACK = 5
    MAXLOCALS = 1

  // access flags 0x0
  $$robo$$GeoPoint_bc6f_toString()Ljava/lang/String;
    ALOAD 0
    INVOKESPECIAL com/google/android/maps/GeoPoint.$$robo$$toString ()Ljava/lang/String;
    ARETURN
    MAXSTACK = 1
    MAXLOCALS = 1

  // access flags 0x1
  public toString()Ljava/lang/String;
    ALOAD 0
    GETFIELD com/google/android/maps/GeoPoint.__robo_data__ : Ljava/lang/Object;
    INSTANCEOF com/google/android/maps/GeoPoint
    IFNE L0
    ALOAD 0
    INVOKESTATIC com/xtremelabs/robolectric/bytecode/RobolectricInternals.shouldCallDirectly (Ljava/lang/Object;)Z
    IFEQ L1
   L0
    ALOAD 0
    INVOKESPECIAL com/google/android/maps/GeoPoint.$$robo$$toString ()Ljava/lang/String;
    ARETURN
   L1
    LDC Lcom/google/android/maps/GeoPoint;.class
    LDC "toString"
    ALOAD 0
    ICONST_0
    ANEWARRAY java/lang/String
    ICONST_0
    ANEWARRAY java/lang/Object
    INVOKESTATIC com/xtremelabs/robolectric/bytecode/RobolectricInternals.methodInvoked (Ljava/lang/Class;Ljava/lang/String;Ljava/lang/Object;[Ljava/lang/String;[Ljava/lang/Object;)Ljava/lang/Object;
    CHECKCAST java/lang/String
    ARETURN
    MAXSTACK = 5
    MAXLOCALS = 1

  // access flags 0x0
  $$robo$$GeoPoint_bc6f_equals(Ljava/lang/Object;)Z
    ALOAD 0
    ALOAD 1
    INVOKESPECIAL com/google/android/maps/GeoPoint.$$robo$$equals (Ljava/lang/Object;)Z
    IRETURN
    MAXSTACK = 2
    MAXLOCALS = 2

  // access flags 0x1
  public equals(Ljava/lang/Object;)Z
    ALOAD 0
    GETFIELD com/google/android/maps/GeoPoint.__robo_data__ : Ljava/lang/Object;
    INSTANCEOF com/google/android/maps/GeoPoint
    IFNE L0
    ALOAD 0
    INVOKESTATIC com/xtremelabs/robolectric/bytecode/RobolectricInternals.shouldCallDirectly (Ljava/lang/Object;)Z
    IFEQ L1
   L0
    ALOAD 0
    ALOAD 1
    INVOKESPECIAL com/google/android/maps/GeoPoint.$$robo$$equals (Ljava/lang/Object;)Z
    IRETURN
   L1
    LDC Lcom/google/android/maps/GeoPoint;.class
    LDC "equals"
    ALOAD 0
    ICONST_1
    ANEWARRAY java/lang/String
    DUP
    ICONST_0
    LDC "java.lang.Object"
    AASTORE
    ICONST_1
    ANEWARRAY java/lang/Object
    DUP
    ICONST_0
    ALOAD 1
    AASTORE
    INVOKESTATIC com/xtremelabs/robolectric/bytecode/RobolectricInternals.methodInvoked (Ljava/lang/Class;Ljava/lang/String;Ljava/lang/Object;[Ljava/lang/String;[Ljava/lang/Object;)Ljava/lang/Object;
    DUP
    IFNONNULL L2
    POP
    ICONST_0
    GOTO L3
   L2
    CHECKCAST java/lang/Boolean
    INVOKEVIRTUAL java/lang/Boolean.booleanValue ()Z
   L3
    IRETURN
    MAXSTACK = 8
    MAXLOCALS = 2

  // access flags 0x0
  $$robo$$GeoPoint_bc6f_hashCode()I
    ALOAD 0
    INVOKESPECIAL com/google/android/maps/GeoPoint.$$robo$$hashCode ()I
    IRETURN
    MAXSTACK = 1
    MAXLOCALS = 1

  // access flags 0x1
  public hashCode()I
    ALOAD 0
    GETFIELD com/google/android/maps/GeoPoint.__robo_data__ : Ljava/lang/Object;
    INSTANCEOF com/google/android/maps/GeoPoint
    IFNE L0
    ALOAD 0
    INVOKESTATIC com/xtremelabs/robolectric/bytecode/RobolectricInternals.shouldCallDirectly (Ljava/lang/Object;)Z
    IFEQ L1
   L0
    ALOAD 0
    INVOKESPECIAL com/google/android/maps/GeoPoint.$$robo$$hashCode ()I
    IRETURN
   L1
    LDC Lcom/google/android/maps/GeoPoint;.class
    LDC "hashCode"
    ALOAD 0
    ICONST_0
    ANEWARRAY java/lang/String
    ICONST_0
    ANEWARRAY java/lang/Object
    INVOKESTATIC com/xtremelabs/robolectric/bytecode/RobolectricInternals.methodInvoked (Ljava/lang/Class;Ljava/lang/String;Ljava/lang/Object;[Ljava/lang/String;[Ljava/lang/Object;)Ljava/lang/Object;
    DUP
    IFNONNULL L2
    POP
    ICONST_0
    GOTO L3
   L2
    CHECKCAST java/lang/Number
    INVOKEVIRTUAL java/lang/Number.intValue ()I
   L3
    IRETURN
    MAXSTACK = 5
    MAXLOCALS = 1

  // access flags 0x1
  // signature ()V
  // declaration: void <init>()
  public <init>()V
    ALOAD 0
    INVOKESPECIAL java/lang/Object.<init> ()V
    RETURN
    MAXSTACK = 1
    MAXLOCALS = 1

  // access flags 0x1
  public <init>(Lcom/xtremelabs/robolectric/bytecode/DirectObjectMarker;Lcom/google/android/maps/GeoPoint;)V
    ALOAD 0
    INVOKESPECIAL java/lang/Object.<init> ()V
    ALOAD 0
    ALOAD 2
    PUTFIELD com/google/android/maps/GeoPoint.__robo_data__ : Ljava/lang/Object;
    RETURN
    MAXSTACK = 2
    MAXLOCALS = 3
}
